LICENSE
README.md
setup.py
cloudweave/__init__.py
cloudweave/auth_manager.py
cloudweave/autoscale_manager.py
cloudweave/database_manager.py
cloudweave/logging_function.py
cloudweave/logging_manager.py
cloudweave/metadata.py
cloudweave/notification_manager.py
cloudweave/storage_manager.py
cloudweave/utilities.py
cloudweave.egg-info/PKG-INFO
cloudweave.egg-info/SOURCES.txt
cloudweave.egg-info/dependency_links.txt
cloudweave.egg-info/requires.txt
cloudweave.egg-info/top_level.txt
cloudweave/autoscale_utils/__init__.py
cloudweave/autoscale_utils/async_utils.py
cloudweave/autoscale_utils/aws_autoscale_utils.py
cloudweave/autoscale_utils/data_utils.py
cloudweave/autoscale_utils/exceptions.py
cloudweave/autoscale_utils/gcp_autoscale_utils.py
cloudweave/autoscale_utils/state_manager.py
cloudweave/cloud_session_utils/__init__.py
cloudweave/cloud_session_utils/aws_session_manager.py
cloudweave/cloud_session_utils/gcp_session_manager.py
cloudweave/database_utils/__init__.py
cloudweave/database_utils/dynamo_manager.py
cloudweave/database_utils/firestore_manager.py
cloudweave/database_utils/mongo_manager.py
cloudweave/logging_utils/__init__.py
cloudweave/logging_utils/aws_logging.py
cloudweave/logging_utils/gcp_logging.py
cloudweave/logging_utils/local_logging.py
cloudweave/logging_utils/string_logger.py
cloudweave/notification_utils/__init__.py
cloudweave/notification_utils/aws_email_manager.py
cloudweave/notification_utils/gcp_email_manager.py
cloudweave/secret_utils/__init__.py
cloudweave/secret_utils/aws_secret_manager.py
cloudweave/secret_utils/class_utils.py
cloudweave/secret_utils/gcp_secret_manager.py
cloudweave/storage_utils/__init__.py
cloudweave/storage_utils/aws_s3_utils.py
cloudweave/storage_utils/gcp_storage_utils.py
tests/test_dynamo.py
tests/test_firestore.py
tests/test_logging.py
tests/test_notification_manager.py
tests/test_storage_manager.py