Metadata-Version: 2.1
Name: cloudweave
Version: 1.0.4
Summary: A unified, authenticated multi-cloud utility package
Home-page: https://github.com/macbee280/cloudweave
Author: Gabe DiMartino
Author-email: gdimartino@gabedimartino.com
Classifier: Development Status :: 4 - Beta
Classifier: Intended Audience :: Developers
Classifier: Topic :: Software Development :: Libraries :: Python Modules
Classifier: License :: OSI Approved :: MIT License
Classifier: Programming Language :: Python :: 3
Classifier: Programming Language :: Python :: 3.7
Classifier: Programming Language :: Python :: 3.8
Classifier: Programming Language :: Python :: 3.9
Classifier: Programming Language :: Python :: 3.10
Classifier: Programming Language :: Python :: 3.11
Classifier: Operating System :: OS Independent
Requires-Python: >=3.7
License-File: LICENSE
Requires-Dist: pydantic>=2.0.0
Requires-Dist: typing-extensions>=4.0.0
Requires-Dist: boto3>=1.26.0
Requires-Dist: botocore>=1.29.0
Requires-Dist: mypy_boto3_ecs
Requires-Dist: mypy_boto3_ec2
Requires-Dist: mypy_boto3_autoscaling
Requires-Dist: mypy_boto3_dynamodb
Requires-Dist: mypy_boto3_sqs
Requires-Dist: mypy_boto3_s3
Requires-Dist: mypy_boto3_secretsmanager
Requires-Dist: mypy_boto3_ses
Requires-Dist: mypy_boto3_logs
Requires-Dist: mypy_boto3_cloudwatch
Requires-Dist: firebase-admin>=6.0.0
Requires-Dist: google-cloud-firestore>=2.10.0
Requires-Dist: google-auth
Requires-Dist: google-cloud-storage
Requires-Dist: google-cloud-bigquery
Requires-Dist: google-cloud-pubsub
Requires-Dist: google-cloud-datastore
Requires-Dist: google-cloud-spanner
Requires-Dist: google-cloud-translate
Requires-Dist: google-cloud-logging
Requires-Dist: google-cloud-vision
Requires-Dist: google-cloud-language
Requires-Dist: google-cloud-secret-manager
Requires-Dist: google-cloud-monitoring
Requires-Dist: pymongo>=4.3.0
Requires-Dist: uuid>=1.30.0
